Metadata-Version: 2.1
Name: text-processing-nlp-tools
Version: 0.0.9
Summary: 文本处理
Home-page: https://github.com/lianyongxing/
Author: tianran
Author-email: 512796933@qq.com
License: UNKNOWN
Platform: UNKNOWN
